{"manifests":[{"annotations":{"com.docker.official-images.bashbrew.arch":"amd64","org.opencontainers.image.base.digest":"sha256:79ff19e9084a00eece421b2523fb93e22d730e2c0e525905de047e848e56d95f","org.opencontainers.image.base.name":"alpine:3.24","org.opencontainers.image.created":"2026-06-16T00:19:20Z","org.opencontainers.image.revision":"b8045df4f76b173c45f9499ca5aa5a82c591a993","org.opencontainers.image.source":"https:\/\/github.com\/corretto\/corretto-docker.git#b8045df4f76b173c45f9499ca5aa5a82c591a993:21\/jdk\/alpine\/3.24","org.opencontainers.image.url":"https:\/\/hub.docker.com\/_\/amazoncorretto","org.opencontainers.image.version":"21-alpine3.24"},"digest":"sha256:587f762f9434bbc18397adbc5bdcd8712672d53993a6fec1d7af219ed1f80fcf","mediaType":"application\/vnd.oci.image.manifest.v1+json","platform":{"architecture":"amd64","os":"linux"},"size":1366},{"annotations":{"com.docker.official-images.bashbrew.arch":"amd64","vnd.docker.reference.digest":"sha256:587f762f9434bbc18397adbc5bdcd8712672d53993a6fec1d7af219ed1f80fcf","vnd.docker.reference.type":"attestation-manifest"},"digest":"sha256:832e2292f3c878a82d7514223e827313a6e637fcb9b56639f79efb4af22448c7","mediaType":"application\/vnd.oci.image.manifest.v1+json","platform":{"architecture":"unknown","os":"unknown"},"size":840},{"annotations":{"com.docker.official-images.bashbrew.arch":"arm64v8","org.opencontainers.image.base.digest":"sha256:e7a1a92a5bfeee40966aea60f0796b0e7917cc35591542701834f03a68fa3d18","org.opencontainers.image.base.name":"alpine:3.24","org.opencontainers.image.created":"2026-06-16T00:17:29Z","org.opencontainers.image.revision":"b8045df4f76b173c45f9499ca5aa5a82c591a993","org.opencontainers.image.source":"https:\/\/github.com\/corretto\/corretto-docker.git#b8045df4f76b173c45f9499ca5aa5a82c591a993:21\/jdk\/alpine\/3.24","org.opencontainers.image.url":"https:\/\/hub.docker.com\/_\/amazoncorretto","org.opencontainers.image.version":"21-alpine3.24"},"digest":"sha256:dc43b39c47f1729dc772a9b8af7222757fac6c8cfa8a0802829af665b1c89925","mediaType":"application\/vnd.oci.image.manifest.v1+json","platform":{"architecture":"arm64","os":"linux","variant":"v8"},"size":1368},{"annotations":{"com.docker.official-images.bashbrew.arch":"arm64v8","vnd.docker.reference.digest":"sha256:dc43b39c47f1729dc772a9b8af7222757fac6c8cfa8a0802829af665b1c89925","vnd.docker.reference.type":"attestation-manifest"},"digest":"sha256:14742d4487c819e19bed3785c6aab130a62752b609a35b6ff8fd399b7c6b2f84","mediaType":"application\/vnd.oci.image.manifest.v1+json","platform":{"architecture":"unknown","os":"unknown"},"size":840}],"mediaType":"application\/vnd.oci.image.index.v1+json","schemaVersion":2}